leet/__init__.py
leet/main.py
leet-0.1.2.dist-info/LICENSE
leet-0.1.2.dist-info/METADATA
leet-0.1.2.dist-info/WHEEL
leet-0.1.2.dist-info/entry_points.txt
leet-0.1.2.dist-info/top_level.txt
leet-0.1.2.dist-info/RECORD
