Metadata-Version: 2.1
Name: leet
Version: 0.1.2
Summary: Leet library 
Home-page: https://github.com/JaneTurueva/py-leet
Author: Evgenia Turueva
Author-email: tindomirel1994@gmail.com
License: MIT
Platform: all
Classifier: Environment :: Console
Classifier: Intended Audience :: Developers
Classifier: License :: OSI Approved :: MIT License
Classifier: Natural Language :: English
Classifier: Operating System :: MacOS
Classifier: Operating System :: POSIX
Classifier: Programming Language :: Python
Classifier: Programming Language :: Python :: 3
Classifier: Programming Language :: Python :: 3.4
Classifier: Programming Language :: Python :: 3.5
Classifier: Programming Language :: Python :: 3.6
Classifier: Programming Language :: Python :: 3.7
Classifier: Programming Language :: Python :: Implementation :: PyPy
Classifier: Programming Language :: Python :: Implementation :: CPython
Classifier: Topic :: Software Development
Classifier: Topic :: Software Development :: Libraries
Requires-Python: >3.4.*, <4
Provides-Extra: develop
Requires-Dist: coverage (!=4.3); extra == 'develop'
Requires-Dist: coveralls; extra == 'develop'
Requires-Dist: pylama; extra == 'develop'
Requires-Dist: pytest; extra == 'develop'
Requires-Dist: pytest-cov; extra == 'develop'
Requires-Dist: tox; extra == 'develop'
Requires-Dist: twine; extra == 'develop'
